joylee_jujube_pill/__init__.py
joylee_jujube_pill-0.0.2.dist-info/METADATA
joylee_jujube_pill-0.0.2.dist-info/WHEEL
joylee_jujube_pill-0.0.2.dist-info/top_level.txt
joylee_jujube_pill-0.0.2.dist-info/RECORD
