Metadata-Version: 2.1
Name: joylee-jujube-pill
Version: 0.0.2
Summary: 吃枣药丸
Home-page: https://zhuanlan.zhihu.com/p/26159930
Author: joylee
Author-email: 1025012627@qq.com
License: UNKNOWN
Platform: UNKNOWN
